retrolover/retrolover.py
retrolover-1.1.0.dist-info/METADATA
retrolover-1.1.0.dist-info/WHEEL
retrolover-1.1.0.dist-info/entry_points.txt
retrolover-1.1.0.dist-info/top_level.txt
retrolover-1.1.0.dist-info/RECORD
