Metadata-Version: 2.1
Name: retrolover
Version: 1.1.0
Summary: Tool for downloading ROMS for your retropie
Home-page: https://github.com/skvoter/retrolover
Author: Kirill Korovin
Author-email: skvoter46@gmail.com
License: UNKNOWN
Platform: UNKNOWN
Classifier: Development Status :: 5 - Production/Stable
Classifier: Programming Language :: Python :: 3 :: Only
Requires-Python: >=3
Requires-Dist: beautifulsoup4
Requires-Dist: requests
